palettepal/__init__.py
palettepal/__main__.py
palettepal/colorapp.py
palettepal/palette.py
palettepal/slider.py
palettepal-0.1.1.dist-info/LICENSE
palettepal-0.1.1.dist-info/METADATA
palettepal-0.1.1.dist-info/WHEEL
palettepal-0.1.1.dist-info/entry_points.txt
palettepal-0.1.1.dist-info/top_level.txt
palettepal-0.1.1.dist-info/zip-safe
palettepal-0.1.1.dist-info/RECORD
