Metadata-Version: 2.1
Name: palettepal
Version: 0.1.1
Summary: Terminal-Based Color Editor and Palette Generator
Home-page: https://github.com/cdelker/palettepal
Author: Collin J. Delker
Author-email: code@collindelker.com
License: License :: OSI Approved :: MIT License
Keywords: color,palette,rgb,ryb,hsl,textual,tui
Classifier: Development Status :: 3 - Alpha
Classifier: Programming Language :: Python
Classifier: Topic :: Multimedia :: Graphics
Classifier: License :: OSI Approved :: MIT License
License-File: LICENSE
Requires-Dist: textual (>=0.30)
Requires-Dist: pyperclip
